README.md
setup.cfg
setup.py
pointbreak/__init__.py
pointbreak/utils.py
pointbreak.egg-info/PKG-INFO
pointbreak.egg-info/SOURCES.txt
pointbreak.egg-info/dependency_links.txt
pointbreak.egg-info/requires.txt
pointbreak.egg-info/top_level.txt