Metadata-Version: 2.1
Name: pointbreak
Version: 0.0.2
Summary: System process debug and analysis library.
Home-page: https://github.com/tonysimpson/pointbreak
Author: Tony Simpson
Author-email: agjasimpson@gmail.com
License: UNKNOWN
Platform: UNKNOWN
Classifier: Programming Language :: Python :: 2.7
Classifier: Programming Language :: Python :: 3
Classifier: License :: OSI Approved :: MIT License
Classifier: Operating System :: POSIX :: Linux
